turberfield_dialogue-0.47.0-py3.9-nspkg.pth
turberfield/dialogue/__init__.py
turberfield/dialogue/adapters.py
turberfield/dialogue/cli.py
turberfield/dialogue/directives.py
turberfield/dialogue/handlers.py
turberfield/dialogue/main.py
turberfield/dialogue/matcher.py
turberfield/dialogue/model.py
turberfield/dialogue/performer.py
turberfield/dialogue/player.py
turberfield/dialogue/schema.py
turberfield/dialogue/types.py
turberfield/dialogue/viewer.py
turberfield/dialogue/doc/api.rst
turberfield/dialogue/doc/battle.rst
turberfield/dialogue/doc/changes.rst
turberfield/dialogue/doc/cli.rst
turberfield/dialogue/doc/cloak.rst
turberfield/dialogue/doc/index.rst
turberfield/dialogue/doc/install.rst
turberfield/dialogue/doc/intro.rst
turberfield/dialogue/doc/performing.rst
turberfield/dialogue/doc/publishing.rst
turberfield/dialogue/doc/syntax.rst
turberfield/dialogue/doc/html/api.html
turberfield/dialogue/doc/html/battle.html
turberfield/dialogue/doc/html/changes.html
turberfield/dialogue/doc/html/cli.html
turberfield/dialogue/doc/html/cloak.html
turberfield/dialogue/doc/html/genindex.html
turberfield/dialogue/doc/html/index.html
turberfield/dialogue/doc/html/install.html
turberfield/dialogue/doc/html/intro.html
turberfield/dialogue/doc/html/performing.html
turberfield/dialogue/doc/html/publishing.html
turberfield/dialogue/doc/html/py-modindex.html
turberfield/dialogue/doc/html/search.html
turberfield/dialogue/doc/html/searchindex.js
turberfield/dialogue/doc/html/syntax.html
turberfield/dialogue/doc/html/_sources/api.rst.txt
turberfield/dialogue/doc/html/_sources/battle.rst.txt
turberfield/dialogue/doc/html/_sources/changes.rst.txt
turberfield/dialogue/doc/html/_sources/cli.rst.txt
turberfield/dialogue/doc/html/_sources/cloak.rst.txt
turberfield/dialogue/doc/html/_sources/index.rst.txt
turberfield/dialogue/doc/html/_sources/install.rst.txt
turberfield/dialogue/doc/html/_sources/intro.rst.txt
turberfield/dialogue/doc/html/_sources/performing.rst.txt
turberfield_dialogue-0.47.0.dist-info/COPYING
turberfield_dialogue-0.47.0.dist-info/LICENSE
turberfield_dialogue-0.47.0.dist-info/METADATA
turberfield_dialogue-0.47.0.dist-info/WHEEL
turberfield_dialogue-0.47.0.dist-info/entry_points.txt
turberfield_dialogue-0.47.0.dist-info/namespace_packages.txt
turberfield_dialogue-0.47.0.dist-info/top_level.txt
turberfield_dialogue-0.47.0.dist-info/RECORD
