Metadata-Version: 2.1
Name: turberfield-dialogue
Version: 0.47.0
Summary: Scripting dialogue and soundtrack for your Turberfield project.
Home-page: https://github.com/tundish/turberfield-dialogue/issues
Author: D Haynes
Author-email: tundish@gigeconomy.org.uk
Classifier: Operating System :: POSIX
Classifier: Programming Language :: Python :: 3.4
Classifier: License :: OSI Approved :: GNU General Public License v3 or later (GPLv3+)
License-File: LICENSE
License-File: COPYING
Requires-Dist: docutils (>=0.17.1)
Requires-Dist: turberfield-utils (>=0.47.0)
Provides-Extra: dev
Requires-Dist: flake8 ; extra == 'dev'
Requires-Dist: wheel ; extra == 'dev'
Provides-Extra: docbuild
Requires-Dist: babel (>=2.4.0) ; extra == 'docbuild'
Requires-Dist: sphinx (>=1.6.1) ; extra == 'docbuild'
Requires-Dist: sphinx-argparse (>=0.2.0) ; extra == 'docbuild'
Requires-Dist: sphinxcontrib-seqdiag (>=0.8.5) ; extra == 'docbuild'
Requires-Dist: sphinx-rtd-theme (>=1.0.0) ; extra == 'docbuild'
Provides-Extra: play
Requires-Dist: blessings (>=1.6) ; extra == 'play'
Requires-Dist: simpleaudio (>=1.0.1) ; extra == 'play'
